ideapad_cm/__init__.py
ideapad_cm/main.py
ideapad_cm/battery/Battery.py
ideapad_cm/battery/CantReadStatusError.py
ideapad_cm/battery/ConservationMode.py
ideapad_cm/battery/__init__.py
ideapad_cm/utils/SysEchoToFile.py
ideapad_cm/utils/SysRunner.py
ideapad_cm/utils/__init__.py
ideapad_cm-0.1.3.dist-info/LICENSE
ideapad_cm-0.1.3.dist-info/METADATA
ideapad_cm-0.1.3.dist-info/WHEEL
ideapad_cm-0.1.3.dist-info/entry_points.txt
ideapad_cm-0.1.3.dist-info/top_level.txt
ideapad_cm-0.1.3.dist-info/RECORD
