Metadata-Version: 2.1
Name: ideapad-cm
Version: 0.1.3
Summary: A rewrite of ideapad-cm with improved systemd and GNOME 3 integration.
Home-page: https://github.com/devaminb/ideapad-cm-rewrite
Author: devaminb
Author-email: devaminb@anonymous.invalid
Project-URL: Bug Tracker, https://github.com/devaminb/ideapad-cm-rewrite/issues
Classifier: Programming Language :: Python :: 3
Classifier: License :: OSI Approved :: GNU General Public License v3 (GPLv3)
Classifier: Operating System :: OS Independent
Requires-Python: >=3.7
License-File: LICENSE
Requires-Dist: click (==8.1.3)
